thonnycontrib/tdmclient_ty/__init__.py
thonnycontrib/tdmclient_ty/res/thymio.run.png
thonnycontrib/tdmclient_ty/res/thymio.stop.png
tdmclient_ty-0.1.9.dist-info/LICENSE
tdmclient_ty-0.1.9.dist-info/METADATA
tdmclient_ty-0.1.9.dist-info/WHEEL
tdmclient_ty-0.1.9.dist-info/top_level.txt
tdmclient_ty-0.1.9.dist-info/RECORD
