Metadata-Version: 2.1
Name: tdmclient-ty
Version: 0.1.9
Summary: Communication with Thymio II robot from Thonny via the Thymio Device Manager
Home-page: https://github.com/epfl-mobots/tdmclient-ty
Author: Yves Piguet
License: UNKNOWN
Platform: UNKNOWN
Classifier: Programming Language :: Python :: 3
Classifier: License :: OSI Approved :: BSD License
Classifier: Intended Audience :: Education
Requires-Python: >=3.6
License-File: LICENSE
Requires-Dist: tdmclient
